shipzo_divide/__init__.py
shipzo_divide/divide.py
shipzo_divide_hun-0.1.0.dist-info/METADATA
shipzo_divide_hun-0.1.0.dist-info/WHEEL
shipzo_divide_hun-0.1.0.dist-info/entry_points.txt
shipzo_divide_hun-0.1.0.dist-info/top_level.txt
shipzo_divide_hun-0.1.0.dist-info/RECORD
