Metadata-Version: 2.4
Name: shipzo_divide_hun
Version: 0.1.0
Summary: Default template for PDM package
Author-email: hun0219 <gsw98000@gmail.com>
License: MIT
Project-URL: Homepage, https://github.com/hun0219/shipzo_divide
Project-URL: Issues, https://github.com/hun0219/shipzo_divide/Issues
Requires-Python: >=3.9
